{
  "config": {
    "age_col": "age",
    "allow_borrowing": false,
    "borrowing_interest_rate": 0.06,
    "borrowing_limit": 0.0,
    "consumption_floor": 1e-08,
    "ct_automatic_illiquid_income_share": 0.05,
    "ct_convergence_tol": 1e-05,
    "ct_convex_adjustment_cost": 8.0,
    "ct_delta_base": 0.5,
    "ct_delta_max": 100000000.0,
    "ct_discount_rate": null,
    "ct_illiquid_cost_floor": 1e-06,
    "ct_linear_adjustment_cost": 0.05,
    "ct_max_iterations": 20,
    "ct_policy_drift_clip": 10000.0,
    "ct_slow_iterations": 20,
    "ct_time_step": 1.0,
    "current_income_col": "current_income",
    "dense_liquid_upper": 0.75,
    "discount_factor": 0.97,
    "education_col": "education",
    "empirical_min_cell_count": 25,
    "empirical_transition_smoothing": 0.001,
    "employed_col": "employed",
    "employment_state_col": "employment_state",
    "gross_income_col": "gross_income",
    "group_col": "group",
    "id_col": "household_id",
    "illiquid_col": "illiquid_assets",
    "illiquid_grid_size": 15,
    "illiquid_interest_rate": 0.02,
    "illiquid_max": 5.0,
    "illiquid_min": 1e-06,
    "illiquid_service_flow": 0.0,
    "income_grid_size": 12,
    "income_state_col": "income_state",
    "labor_income_col": "labor_income",
    "liquid_col": "liquid_assets",
    "liquid_grid_size": 100,
    "liquid_interest_rate": 0.0,
    "liquid_max": 2.0,
    "liquid_service_flow": 0.0,
    "max_age": 80,
    "min_age": 25,
    "normalize_empirical_money": true,
    "pension_col": "pension_income",
    "potential_labor_col": "potential_labor_income",
    "retirement_age": 65,
    "risk_aversion": 6.0,
    "seed": 12345,
    "taxes_col": "taxes",
    "unemployment_col": "unemployment_benefits",
    "year_col": "year"
  },
  "diagnostics": {
    "max_distance": 9.055483360498329e-06,
    "max_iterations": 9,
    "message": "",
    "model_id": "a8aacca1eb6135",
    "status": "success"
  },
  "metadata": {
    "chi0": 0.05,
    "chi1": 8.0,
    "ra_ct": 0.019802627296179712,
    "rb_neg_ct": 0.058268908123975775,
    "rb_pos_ct": 0.0,
    "rho_ct": 0.030459207484708574,
    "xi": 0.05
  },
  "money_scale": 1.0,
  "policy_bundle_metadata": {
    "source": "parametric",
    "spec": {
      "bundle_path": null,
      "employment": {
        "finding_income_slope": 0.0,
        "job_finding_probability": 0.85,
        "job_loss_probability": 0.075,
        "kind": "constant",
        "loss_income_slope": 0.0,
        "name": "emp_loss0.075_find0.85",
        "retirement_absorbing": true,
        "unemployment_replacement_rate": 0.7
      },
      "group_values": [
        0
      ],
      "income": {
        "age_profile_quadratic": -0.1,
        "age_profile_slope": 0.4,
        "group_log_income_shifters": [
          0.0
        ],
        "innovation_std": 0.1,
        "kind": "rouwenhorst",
        "mean_income": 1.0,
        "name": "income_rho0.90_sig0.10",
        "persistence": 0.9
      },
      "name": "income_rho0.90_sig0.10__emp_loss0.075_find0.85__tax_none_flat0.15_prog0.02__pension_rr0.25",
      "pension": {
        "kind": "replacement_rate",
        "name": "pension_rr0.25",
        "pension_taxable": true,
        "replacement_rate": 0.25
      },
      "source": "parametric",
      "tax": {
        "deduction": 0.2,
        "flat_rate": 0.15,
        "kind": "none",
        "name": "tax_none_flat0.15_prog0.02",
        "payroll_rate": 0.08,
        "progressive_exponent": 1.35,
        "progressive_rate": 0.02,
        "tax_cap": 0.95
      }
    }
  },
  "policy_bundle_name": "income_rho0.90_sig0.10__emp_loss0.075_find0.85__tax_none_flat0.15_prog0.02__pension_rr0.25",
  "saved_arrays": {
    "dtype": "float32",
    "transitions": true,
    "value": false
  }
}